txbit/__init__.py
txbit/txbit.py
txbit/tests/__init__.py
txbit/tests/test.py
txbit-1.0.0.dist-info/LICENSE
txbit-1.0.0.dist-info/METADATA
txbit-1.0.0.dist-info/WHEEL
txbit-1.0.0.dist-info/top_level.txt
txbit-1.0.0.dist-info/RECORD
