Metadata-Version: 2.1
Name: txbit
Version: 1.0.0
Summary: A Python wrapper for the Txbit API
Home-page: https://github.com/AD-Ventures/txbit
Author: AD Ventures
Author-email: abir.dahlin.ventures@gmail.com
License: UNKNOWN
Platform: UNKNOWN
Classifier: Programming Language :: Python :: 3
Classifier: License :: OSI Approved :: MIT License
Classifier: Operating System :: OS Independent
Requires-Python: >=3.3
Requires-Dist: requests
